Practical-4_Joab/src/Parameter.v
// =========================================================================
// Practical 4: StarCore-1 — Single-Cycle Processor in Verilog
// =========================================================================
//
// GROUP NUMBER:7
//
// MEMBERS:
//   - Member 1 Joab Gray Kloppers, KLPJOA002
//   - Member 2 Name, Student Number

// File        : Parameter.v
// Description : Shared compile-time parameters used across all modules.
//               Include this file at the top of every .v file:
//                   `include "../src/Parameter.v"
// =============================================================================

`ifndef PARAMETER_H_
`define PARAMETER_H_

// ---------------------------------------------------------------------------
// Memory dimensions
// ---------------------------------------------------------------------------
`define COL     16          // Data/instruction word width (bits)
`define ROW_I   16          // Instruction memory depth (words, 16 x 16-bit)
`define ROW_D    8          // Data memory depth (words,  8 x 16-bit)

// ---------------------------------------------------------------------------
// Simulation control
// Increase SIM_TIME if your test program needs more clock cycles to complete.
// At 10 ns per clock (100 MHz) each #10 is one half-period; 320 ns = 16 cycles.
// ---------------------------------------------------------------------------
`define SIM_TIME  #640      // Total simulation time for integration testbench

// ---------------------------------------------------------------------------
// Output file for data-memory dump (used in DataMemory.v $fmonitor)
// ---------------------------------------------------------------------------
`define DMEM_LOG  "./waves/dmem_log.txt"

`endif  // PARAMETER_H_

Practical-4_Joab/src/ALU_Control.v
// =========================================================================
// Practical 4: StarCore-1 — Single-Cycle Processor in Verilog
// =========================================================================
//
// GROUP NUMBER: 7
//
// MEMBERS:
//   - Member 1 Joab Gray Kloppers, KLPJOA002
//   - Member 2 Name, Student Number

// File        : ALU_Control.v
// Description : ALU Control Unit.
//               Maps the 2-bit ALUOp signal (from the Main Control Unit) and
//               the 4-bit instruction opcode to the 3-bit ALUcnt signal that
//               drives the ALU's operation select input.
//               This is a purely combinational module.
//
// Task 5 — Student Implementation Required
// =============================================================================

`timescale 1ns / 1ps
`include "../src/Parameter.v"

module ALU_Control (
    input  [1:0] ALUOp,         // From ControlUnit:
                                //   2'b10 = memory access (always ADD for address)
                                //   2'b01 = branch      (always SUB for comparison)
                                //   2'b00 = R-type      (decode from opcode)
    input  [3:0] Opcode,        // Instruction opcode field [15:12]
    output reg [2:0] ALU_Cnt    // To ALU alu_control input
);

    // -------------------------------------------------------------------------
    // TODO: Concatenate ALUOp and Opcode into a single 6-bit control word so
    //       you can use a casex statement with don't-care bits.
    //
    //       wire [5:0] control_in;
    //       assign control_in = {ALUOp, Opcode};
    //
    //       The casex truth table (from Section 3.4 of the manual):
    //
    //       control_in | ALU_Cnt | Operation   | Instruction
    //       -----------+---------+-------------+------------------
    //       6'b10xxxx  |  3'b000 | ADD         | LD, ST
    //       6'b01xxxx  |  3'b001 | SUB         | BEQ, BNE
    //       6'b000010  |  3'b000 | ADD         | ADD
    //       6'b000011  |  3'b001 | SUB         | SUB
    //       6'b000100  |  3'b010 | INV (NOT)   | INV
    //       6'b000101  |  3'b011 | SHL         | SHL
    //       6'b000110  |  3'b100 | SHR         | SHR
    //       6'b000111  |  3'b101 | AND         | AND
    //       6'b001000  |  3'b110 | OR          | OR
    //       6'b001001  |  3'b111 | SLT         | SLT
    //       default    |  3'b000 | ADD (safe)  | reserved / undefined
    //
    //       Implement using:
    //           always @(*) begin
    //               casex (control_in)
    //                   6'b10xxxx : ALU_Cnt = 3'b000;
    //                   ...
    //                   default   : ALU_Cnt = 3'b000;
    //               endcase
    //           end
    //
    //       IMPORTANT: The 'x' in casex patterns matches any logic value
    //       (0, 1, X, or Z). This correctly encodes don't-care bits for the
    //       opcode field when ALUOp selects memory or branch mode.
    // -------------------------------------------------------------------------
    wire [5:0] control_in;
    assign control_in = {ALUOp,Opcode};

    always @(*) begin
        casex (control_in)
            6'b10xxxx : ALU_Cnt = 3'b000;
            6'b01xxxx : ALU_Cnt = 3'b001;
            6'b000010 : ALU_Cnt = 3'b000;
            6'b000011 : ALU_Cnt = 3'b001;
            6'b000100 : ALU_Cnt = 3'b010;
            6'b000101 : ALU_Cnt = 3'b011;
            6'b000110 : ALU_Cnt = 3'b100;
            6'b000111 : ALU_Cnt = 3'b101;
            6'b001000 : ALU_Cnt = 3'b110;
            6'b001001 : ALU_Cnt = 3'b111;
            default : ALU_Cnt = 3'b000;
        endcase
    end


endmodule

Practical-4_Joab/tb/ALU_Control_tb.v
// =============================================================================
// EEE4120F Practical 4 — StarCore-1 Processor
// File        : ALU_Control_tb.v
// Description : Testbench for the ALU Control Unit (Task 5).
//               Drives every row of the ALU control truth table and verifies
//               the 3-bit ALUcnt output.
//
// Run:
//   iverilog -Wall -I ../src -o ../build/ac_sim ../src/ALU_Control.v ALU_Control_tb.v
//   cd ../test && ../build/ac_sim
//   gtkwave ../waves/ac_tb.vcd &
// =============================================================================

`timescale 1ns / 1ps
`include "../src/Parameter.v"

module ALU_Control_tb;

    reg  [1:0] ALUOp;
    reg  [3:0] Opcode;
    wire [2:0] ALU_Cnt;

    ALU_Control uut (
        .ALUOp   (ALUOp),
        .Opcode  (Opcode),
        .ALU_Cnt (ALU_Cnt)
    );

    initial begin
        $dumpfile("../waves/ac_tb.vcd");
        $dumpvars(0, ALU_Control_tb);
    end

    integer fail_count;
    integer test_id;

    integer i;

    task check_cnt;
        input [2:0] got;
        input [2:0] expected;
        input [63:0] id;
        begin
            if (got !== expected) begin
                $display("FAIL [T%0d]: ALU_Cnt = %b, expected = %b", id, got, expected);
                fail_count = fail_count + 1;
            end else
                $display("PASS [T%0d]: ALU_Cnt = %b", id, got);
        end
    endtask

    initial begin
        fail_count = 0;
        test_id    = 1;
        $display("=== ALU_Control Testbench ===");

        // ------------------------------------------------------------------
        // ALUOp = 10 (memory access) — always ADD regardless of opcode
        // ------------------------------------------------------------------
        $display("--- ALUOp=10: all opcodes should map to ADD (000) ---");

        // TODO: Apply ALUOp=2'b10 with several different opcode values and
        //       verify ALU_Cnt is always 3'b000 (ADD).
        //
        //       ALUOp=2'b10; Opcode=4'h0; #10;
        //       check_cnt(ALU_Cnt, 3'b000, test_id); test_id=test_id+1;
        //
        //       ALUOp=2'b10; Opcode=4'hF; #10;
        //       check_cnt(ALU_Cnt, 3'b000, test_id); test_id=test_id+1;

        ALUOp = 2'b10; Opcode = 4'h0; #10;
        check_cnt(ALU_Cnt,3'b000,test_id); test_id = test_id +1;

        ALUOp = 2'b10; Opcode = 4'hF; #10;
        check_cnt(ALU_Cnt,3'b000,test_id); test_id = test_id +1;


        // ------------------------------------------------------------------
        // ALUOp = 01 (branch) — always SUB regardless of opcode
        // ------------------------------------------------------------------
        $display("--- ALUOp=01: all opcodes should map to SUB (001) ---");

        // TODO: Apply ALUOp=2'b01 with several opcode values and verify
        //       ALU_Cnt is always 3'b001 (SUB).

        ALUOp = 2'b01; Opcode = 4'h0; #10;
        check_cnt(ALU_Cnt,3'b001,test_id); test_id = test_id +1;

        ALUOp = 2'b01; Opcode = 4'hF; #10;
        check_cnt(ALU_Cnt,3'b001,test_id); test_id = test_id +1;


        // ------------------------------------------------------------------
        // ALUOp = 00 (R-type) — decode from opcode
        // ------------------------------------------------------------------
        $display("--- ALUOp=00: decode per opcode ---");

        // TODO: Apply ALUOp=2'b00 with each R-type opcode and verify:
        //
        //       Opcode 4'h2 (ADD) -> ALU_Cnt = 3'b000
        //       Opcode 4'h3 (SUB) -> ALU_Cnt = 3'b001
        //       Opcode 4'h4 (INV) -> ALU_Cnt = 3'b010
        //       Opcode 4'h5 (SHL) -> ALU_Cnt = 3'b011
        //       Opcode 4'h6 (SHR) -> ALU_Cnt = 3'b100
        //       Opcode 4'h7 (AND) -> ALU_Cnt = 3'b101
        //       Opcode 4'h8 (OR)  -> ALU_Cnt = 3'b110
        //       Opcode 4'h9 (SLT) -> ALU_Cnt = 3'b111
        //
        //       ALUOp=2'b00; Opcode=4'h2; #10;
        //       check_cnt(ALU_Cnt, 3'b000, test_id); test_id=test_id+1;
        //       ... etc.

        ALUOp = 2'b00;
        for (i = 2; i<=9; i = i + 1) begin
            Opcode = i; #10;
            check_cnt(ALU_Cnt,i-2,test_id); test_id = test_id +1;
        end


        // ------------------------------------------------------------------
        // Default case
        // ------------------------------------------------------------------
        $display("--- Default (ALUOp=00, undefined opcode) -> ADD (000) ---");

        // TODO: Apply ALUOp=2'b00 with an undefined opcode (e.g. 4'hA or 4'hF)
        //       and verify ALU_Cnt defaults to 3'b000.
        ALUOp = 2'b00; Opcode = 4'hA; #10;
        check_cnt(ALU_Cnt,3'b000,test_id); test_id = test_id +1;




        $display("");
        if (fail_count == 0)
            $display("=== ALL %0d TESTS PASSED ===", test_id - 1);
        else
            $display("=== %0d / %0d TESTS FAILED ===", fail_count, test_id - 1);
        $finish;
    end

endmodule

Practical-4_Joab/waves/ac_tb.vcd
$date
	Mon Apr 20 23:11:23 2026
$end
$version
	Icarus Verilog
$end
$timescale
	1ps
$end
$scope module ALU_Control_tb $end
$var wire 3 ! ALU_Cnt [2:0] $end
$var reg 2 " ALUOp [1:0] $end
$var reg 4 # Opcode [3:0] $end
$var integer 32 $ fail_count [31:0] $end
$var integer 32 % i [31:0] $end
$var integer 32 & test_id [31:0] $end
$scope module uut $end
$var wire 2 ' ALUOp [1:0] $end
$var wire 4 ( Opcode [3:0] $end
$var wire 6 ) control_in [5:0] $end
$var reg 3 * ALU_Cnt [2:0] $end
$upscope $end
$scope task check_cnt $end
$var reg 3 + expected [2:0] $end
$var reg 3 , got [2:0] $end
$var reg 64 - id [63:0] $end
$upscope $end
$upscope $end
$enddefinitions $end
$comment Show the parameter values. $end
$dumpall
$end
#0
$dumpvars
bx -
bx ,
bx +
b0 *
b100000 )
b0 (
b10 '
b1 &
bx %
b0 $
b0 #
b10 "
b0 !
$end
#10000
b101111 )
b1111 #
b1111 (
b10 &
b1 -
b0 +
b0 ,
#20000
b1 !
b1 *
b0 #
b0 (
b10000 )
b1 "
b1 '
b11 &
b10 -
#30000
b11111 )
b1111 #
b1111 (
b100 &
b11 -
b1 +
b1 ,
#40000
b0 !
b0 *
b10 #
b10 (
b10 %
b10 )
b0 "
b0 '
b101 &
b100 -
#50000
b1 !
b1 *
b11 )
b11 #
b11 (
b11 %
b110 &
b101 -
b0 +
b0 ,
#60000
b10 !
b10 *
b100 )
b100 #
b100 (
b100 %
b111 &
b110 -
b1 +
b1 ,
#70000
b11 !
b11 *
b101 )
b101 #
b101 (
b101 %
b1000 &
b111 -
b10 +
b10 ,
#80000
b100 !
b100 *
b110 )
b110 #
b110 (
b110 %
b1001 &
b1000 -
b11 +
b11 ,
#90000
b101 !
b101 *
b111 )
b111 #
b111 (
b111 %
b1010 &
b1001 -
b100 +
b100 ,
#100000
b110 !
b110 *
b1000 )
b1000 #
b1000 (
b1000 %
b1011 &
b1010 -
b101 +
b101 ,
#110000
b111 !
b111 *
b1001 )
b1001 #
b1001 (
b1001 %
b1100 &
b1011 -
b110 +
b110 ,
#120000
b0 !
b0 *
b1010 )
b1010 #
b1010 (
b1010 %
b1101 &
b1100 -
b111 +
b111 ,
#130000
b1110 &
b1101 -
b0 +
b0 ,
