Practical-4_Joab/src/Parameter.v
// =========================================================================
// Practical 4: StarCore-1 — Single-Cycle Processor in Verilog
// =========================================================================
//
// GROUP NUMBER:7
//
// MEMBERS:
//   - Member 1 Joab Gray Kloppers, KLPJOA002
//   - Member 2 Name, Student Number

// File        : Parameter.v
// Description : Shared compile-time parameters used across all modules.
//               Include this file at the top of every .v file:
//                   `include "../src/Parameter.v"
// =============================================================================

`ifndef PARAMETER_H_
`define PARAMETER_H_

// ---------------------------------------------------------------------------
// Memory dimensions
// ---------------------------------------------------------------------------
`define COL     16          // Data/instruction word width (bits)
`define ROW_I   16          // Instruction memory depth (words, 16 x 16-bit)
`define ROW_D    8          // Data memory depth (words,  8 x 16-bit)

// ---------------------------------------------------------------------------
// Simulation control
// Increase SIM_TIME if your test program needs more clock cycles to complete.
// At 10 ns per clock (100 MHz) each #10 is one half-period; 320 ns = 16 cycles.
// ---------------------------------------------------------------------------
`define SIM_TIME  #640      // Total simulation time for integration testbench

// ---------------------------------------------------------------------------
// Output file for data-memory dump (used in DataMemory.v $fmonitor)
// ---------------------------------------------------------------------------
`define DMEM_LOG  "./waves/dmem_log.txt"

`endif  // PARAMETER_H_

Practical-4_Joab/src/DataMemory.v
// =========================================================================
// Practical 4: StarCore-1 — Single-Cycle Processor in Verilog
// =========================================================================
//
// GROUP NUMBER:7
//
// MEMBERS:
//   - Member 1 Joab Gray Kloppers, KLPJOA002
//   - Member 2 Name, Student Number

// File        : DataMemory.v
// Description : Data Memory (RAM).
//               8 words × 16 bits. Contents loaded at simulation start from
//               the binary file ./test/test.data using $readmemb.
//               Writes are synchronous (positive-edge clocked).
//               Reads are combinational and gated by the mem_read enable.
//
// Task 4 — Student Implementation Required
// =============================================================================

`timescale 1ns / 1ps
`include "../src/Parameter.v"

module DataMemory (
    input        clk,

    // Shared address bus (used for both reads and writes)
    input  [15:0] mem_access_addr,  // Byte address; only lower bits used for indexing

    // Write port
    input  [15:0] mem_write_data,   // Data to store
    input        mem_write_en,      // Assert to write on the next posedge clk

    // Read port
    input        mem_read,          // Assert to enable the read output
    output [15:0] mem_read_data     // Read result; 16'd0 when mem_read is de-asserted
);

    // -------------------------------------------------------------------------
    // TODO: Declare the data memory array.
    //       It should hold `ROW_D entries, each `COL bits wide.
    //
    //       reg [`COL-1:0] memory [`ROW_D-1:0];
    // -------------------------------------------------------------------------
    reg [`COL-1:0] memory [`ROW_D-1:0];    


    // -------------------------------------------------------------------------
    // TODO: Derive the word address from mem_access_addr.
    //       The data memory is 8 words deep so only 3 address bits are needed.
    //       The ALU computes a byte address; use the lower 3 bits as the index:
    //
    //           wire [2:0] ram_addr = mem_access_addr[2:0];
    //
    //       This maps byte addresses 0,1,2,3,4,5,6,7 to words 0–7.
    //       (In a full system the byte offset within a word would also be
    //       handled, but StarCore-1 only supports 16-bit aligned accesses.)
    // -------------------------------------------------------------------------
    wire [2:0] ram_addr = mem_access_addr[2:0];


    // -------------------------------------------------------------------------
    // TODO: Load the data memory from file at simulation start.
    //       The file ./test/test.data must contain one 16-bit binary value
    //       per line (8 lines total, one per word).
    //
    //       integer log_fd;
    //       initial begin
    //           $readmemb("./test/test.data", memory);
    //       end
    //
    //       Optional — add a $fmonitor to log memory contents to a file.
    //       This is useful for verifying ST instructions during simulation:
    //
    //       initial begin
    //           log_fd = $fopen(`DMEM_LOG);
    //           $fmonitor(log_fd, "t=%0t  [0]=%h [1]=%h [2]=%h [3]=%h",
    //                     $time, memory[0], memory[1], memory[2], memory[3]);
    //           `SIM_TIME;
    //           $fclose(log_fd);
    //       end
    // -------------------------------------------------------------------------

    integer log_fd;
    initial begin
        $readmemb("test.data",memory);
    end

    //initial begin
    //    log_fd = $fopen(`DMEM_LOG);
    //    $fmonitor(log_fd, "t=%0t [0]=%h [1]=%h [2]=%h [3]=%h",
    //                $time, memory[0],memory[1],memory[2],memory[3]);
    //    `SIM_TIME;
    //    $fclose(log_fd);
    //end


    // -------------------------------------------------------------------------
    // TODO: Implement the synchronous write port.
    //       Write mem_write_data to memory[ram_addr] on the rising clock edge
    //       when mem_write_en is asserted.
    //
    //       always @(posedge clk) begin
    //           if (mem_write_en)
    //               memory[ram_addr] <= mem_write_data;
    //       end
    //
    //       IMPORTANT: Use non-blocking assignment (<=).
    // -------------------------------------------------------------------------

    always @(posedge clk ) begin
        if (mem_write_en)
            memory[ram_addr] <= mem_write_data;
    end


    // -------------------------------------------------------------------------
    // TODO: Implement the combinational (gated) read port.
    //       When mem_read is 1, output memory[ram_addr].
    //       When mem_read is 0, output 16'd0 (prevents spurious register writes
    //       during non-LD instructions).
    //
    //       assign mem_read_data = mem_read ? memory[ram_addr] : 16'd0;
    // -------------------------------------------------------------------------
    assign mem_read_data = mem_read ? memory[ram_addr] : 16'd0;

endmodule

Practical-4_Joab/tb/DataMemory_tb.v
// =============================================================================
// EEE4120F Practical 4 — StarCore-1 Processor
// File        : DataMemory_tb.v
// Description : Testbench for the Data Memory module (Task 4).
//               Verifies synchronous write, gated combinational read,
//               write followed by immediate read, and disabled-write safety.
//
// Run:
//   iverilog -Wall -I ../src -o ../build/dm_sim ../src/DataMemory.v DataMemory_tb.v
//   cd ../test && ../build/dm_sim
//   gtkwave ../waves/dm_tb.vcd &
// =============================================================================

`timescale 1ns / 1ps
`include "../src/Parameter.v"

module DataMemory_tb;

    reg        clk;
    reg  [15:0] mem_access_addr;
    reg  [15:0] mem_write_data;
    reg        mem_write_en;
    reg        mem_read;
    wire [15:0] mem_read_data;

    DataMemory uut (
        .clk             (clk),
        .mem_access_addr (mem_access_addr),
        .mem_write_data  (mem_write_data),
        .mem_write_en    (mem_write_en),
        .mem_read        (mem_read),
        .mem_read_data   (mem_read_data)
    );

    initial clk = 1'b0;
    always  #5 clk = ~clk;

    initial begin
        $dumpfile("../waves/dm_tb.vcd");
        $dumpvars(0, DataMemory_tb);
    end

    integer fail_count;
    integer test_id;
    integer i;

    reg [15:0] expected [0:7];

    initial begin
        fail_count      = 0;
        test_id         = 1;
        mem_write_en    = 1'b0;
        mem_read        = 1'b0;
        mem_access_addr = 16'd0;
        mem_write_data  = 16'd0;

        expected[0]=16'b0000000000000001;
        expected[1]=16'b0000000000000010;
        expected[2]=16'b0000000000000011;
        expected[3]=16'b0000000000000100;
        expected[4]=16'b0000000000000101;
        expected[5]=16'b0000000000000110;
        expected[6]=16'b0000000000000111;
        expected[7]=16'b0000000000001000;


        $display("=== DataMemory Testbench ===");

        // ------------------------------------------------------------------
        // TEST GROUP 1: Read back initial values loaded from test.data
        // ------------------------------------------------------------------
        $display("--- Group 1: Verify $readmemb initialisation ---");

        // TODO: Read each of the 8 memory locations and verify against
        //       the known contents of your test.data file.
        //       Remember: only mem_access_addr[2:0] is used as the index.
        //       Address 16'd0 -> word 0, address 16'd2 -> word 2, etc.
        //       (Or use address 16'd0 -> word 0, address 16'd1 -> word 1,
        //        since only the lower 3 bits matter.)
        //
        //       mem_read = 1'b1;
        //       mem_access_addr = 16'd0; #5;
        //       if (mem_read_data !== 16'h0001)  // expected value from test.data line 0
        //           $display("FAIL [T%0d]: addr=0 got=0x%h exp=0x0001", test_id, mem_read_data);
        //       else
        //           $display("PASS [T%0d]", test_id);
        //       test_id = test_id + 1;

        
        for(i = 0; i<=7; i = i +1) begin
            mem_read = 1'b1;
            mem_access_addr = i; #5;
            if (mem_read_data !== expected[i]) begin
                $display("FAIL [T%0d]: addr=%0d got=0x%h exp=%x", test_id, i, mem_read_data, expected[i]);
                fail_count = fail_count + 1;
            end else
                $display("PASS [T%0d]", test_id);
            test_id = test_id + 1;
            mem_read = 1'b0;
        end
        



        // ------------------------------------------------------------------
        // TEST GROUP 2: Write new values to all 8 locations, then read back
        // ------------------------------------------------------------------
        $display("--- Group 2: Write then read all 8 locations ---");

        // TODO: Write a distinct value to each of the 8 addresses using
        //       mem_write_en and posedge clk, then read each back.
        //
        //       // Write to address 0
        //       mem_write_en    = 1'b1;
        //       mem_access_addr = 16'd0;
        //       mem_write_data  = 16'hABCD;
        //       @(posedge clk); #1;
        //       mem_write_en    = 1'b0;
        //
        //       // Read back from address 0
        //       mem_read = 1'b1;
        //       mem_access_addr = 16'd0; #5;
        //       if (mem_read_data !== 16'hABCD) ...
        //       test_id = test_id + 1;

        for(i = 0; i<=7; i = i+1) begin
            mem_write_en = 1'b1;
            mem_access_addr = i;
            mem_write_data = 16'hA000 + i;
            @(posedge clk); #1;
            mem_write_en = 1'b0;

            mem_read = 1'b1;
            mem_access_addr = i; #5;
            if (mem_read_data !== 16'hA000 +i) begin 
                $display("FAIL [T%0d]: addr=%0d got=0x%h exp=%x", test_id, i, mem_read_data,16'hA000 +i);
                fail_count = fail_count + 1;
            end else
                $display("PASS [T%0d]", test_id);
            test_id = test_id + 1;
            mem_read = 1'b0;

        end


        // ------------------------------------------------------------------
        // TEST GROUP 3: mem_read = 0 must produce 16'd0 output
        // ------------------------------------------------------------------
        $display("--- Group 3: mem_read disabled -> output must be 0 ---");

        // TODO: De-assert mem_read and verify the output is 16'd0 regardless
        //       of the address.
        //
        //       mem_read = 1'b0;
        //       mem_access_addr = 16'd0; #5;
        //       if (mem_read_data !== 16'd0)
        //           $display("FAIL [T%0d]: mem_read=0 but output=%h", test_id, mem_read_data);
        //       else
        //           $display("PASS [T%0d]: output = 0 when mem_read=0", test_id);
        //       test_id = test_id + 1;

        mem_read = 1'b0;
        mem_access_addr = 16'd0; #5;
        if (mem_read_data !== 16'd0) begin 
            $display("FAIL [T%0d]: mem_read=0 but output=%h", test_id, mem_read_data);
            fail_count = fail_count + 1;
        end else
            $display("PASS [T%0d]: output = 0 when mem_read=0", test_id);
        test_id = test_id + 1;


        // ------------------------------------------------------------------
        // TEST GROUP 4: Write then immediately read on the next cycle
        // ------------------------------------------------------------------
        $display("--- Group 4: Write followed by immediate read ---");

        // TODO: Write to address 3, then on the very next cycle read back
        //       from address 3 and confirm the new value is returned.

        mem_write_en = 1'b1;
        mem_read = 1'b1;
        mem_access_addr = 16'd3;
        mem_write_data = 16'hF0F0;
        @(posedge clk); #1;

        if (mem_read_data !== 16'hF0F0) begin
            $display("FAIL [T%0d]: addr=3 got=0x%h exp=0xF0F0", test_id, mem_read_data);
            fail_count = fail_count + 1;
        end else
            $display("PASS [T%0d]", test_id);
        test_id = test_id + 1;
        mem_read = 1'b0;
        mem_write_en = 1'b0;


        // ------------------------------------------------------------------
        // TEST GROUP 5: Disabled write must not alter memory
        // ------------------------------------------------------------------
        $display("--- Group 5: mem_write_en=0 must not overwrite memory ---");

        // TODO: Assert mem_write_en=0, clock one cycle, then read and confirm
        //       the previous value is unchanged.

        mem_write_en = 1'b0;
        mem_access_addr = 16'd3;
        mem_write_data = 16'h1010;
        @(posedge clk); #1;

        mem_read = 1'b1; #5;
        if (mem_read_data !== 16'hF0F0) begin
            $display("FAIL [T%0d]: addr=3 got=0x%h exp=0xF0F0", test_id, mem_read_data);
            fail_count = fail_count + 1;
        end else
            $display("PASS [T%0d]", test_id);
        test_id = test_id + 1;
        mem_read = 1'b0;
    

        $display("");
        if (fail_count == 0)
            $display("=== ALL %0d TESTS PASSED ===", test_id - 1);
        else
            $display("=== %0d / %0d TESTS FAILED ===", fail_count, test_id - 1);
        $finish;
    end

endmodule

Practical-4_Joab/waves/dm_tb.vcd
$date
	Sun Apr 19 23:18:33 2026
$end
$version
	Icarus Verilog
$end
$timescale
	1ps
$end
$scope module DataMemory_tb $end
$var wire 16 ! mem_read_data [15:0] $end
$var reg 1 " clk $end
$var reg 16 # mem_access_addr [15:0] $end
$var reg 1 $ mem_read $end
$var reg 16 % mem_write_data [15:0] $end
$var reg 1 & mem_write_en $end
$var integer 32 ' fail_count [31:0] $end
$var integer 32 ( i [31:0] $end
$var integer 32 ) test_id [31:0] $end
$scope module uut $end
$var wire 1 " clk $end
$var wire 16 * mem_access_addr [15:0] $end
$var wire 1 $ mem_read $end
$var wire 16 + mem_write_data [15:0] $end
$var wire 1 & mem_write_en $end
$var wire 3 , ram_addr [2:0] $end
$var wire 16 - mem_read_data [15:0] $end
$upscope $end
$upscope $end
$enddefinitions $end
$comment Show the parameter values. $end
$dumpall
$end
#0
$dumpvars
b1 -
b0 ,
b0 +
b0 *
b1 )
b0 (
b0 '
0&
b0 %
1$
b0 #
0"
b1 !
$end
#5000
b10 !
b10 -
b1 ,
b1 #
b1 *
b1 (
1$
b10 )
1"
#10000
b11 !
b11 -
b10 ,
b10 #
b10 *
b10 (
1$
b11 )
0"
#15000
b100 !
b100 -
b11 ,
b11 #
b11 *
b11 (
1$
b100 )
1"
#20000
b101 !
b101 -
b100 ,
b100 #
b100 *
b100 (
1$
b101 )
0"
#25000
b110 !
b110 -
b101 ,
b101 #
b101 *
b101 (
1$
b110 )
1"
#30000
b111 !
b111 -
b110 ,
b110 #
b110 *
b110 (
1$
b111 )
0"
#35000
b1000 !
b1000 -
b111 ,
b111 #
b111 *
b111 (
1$
b1000 )
1"
#40000
b0 ,
b0 !
b0 -
b1010000000000000 %
b1010000000000000 +
b0 #
b0 *
1&
b0 (
0$
b1001 )
0"
#45000
1"
#46000
b1010000000000000 !
b1010000000000000 -
1$
0&
#50000
0"
#51000
b1 ,
b0 !
b0 -
b1010000000000001 %
b1010000000000001 +
b1 #
b1 *
1&
b1 (
0$
b1010 )
#55000
1"
#56000
b1010000000000001 !
b1010000000000001 -
1$
0&
#60000
0"
#61000
b10 ,
b0 !
b0 -
b1010000000000010 %
b1010000000000010 +
b10 #
b10 *
1&
b10 (
0$
b1011 )
#65000
1"
#66000
b1010000000000010 !
b1010000000000010 -
1$
0&
#70000
0"
#71000
b11 ,
b0 !
b0 -
b1010000000000011 %
b1010000000000011 +
b11 #
b11 *
1&
b11 (
0$
b1100 )
#75000
1"
#76000
b1010000000000011 !
b1010000000000011 -
1$
0&
#80000
0"
#81000
b100 ,
b0 !
b0 -
b1010000000000100 %
b1010000000000100 +
b100 #
b100 *
1&
b100 (
0$
b1101 )
#85000
1"
#86000
b1010000000000100 !
b1010000000000100 -
1$
0&
#90000
0"
#91000
b101 ,
b0 !
b0 -
b1010000000000101 %
b1010000000000101 +
b101 #
b101 *
1&
b101 (
0$
b1110 )
#95000
1"
#96000
b1010000000000101 !
b1010000000000101 -
1$
0&
#100000
0"
#101000
b110 ,
b0 !
b0 -
b1010000000000110 %
b1010000000000110 +
b110 #
b110 *
1&
b110 (
0$
b1111 )
#105000
1"
#106000
b1010000000000110 !
b1010000000000110 -
1$
0&
#110000
0"
#111000
b111 ,
b0 !
b0 -
b1010000000000111 %
b1010000000000111 +
b111 #
b111 *
1&
b111 (
0$
b10000 )
#115000
1"
#116000
b1010000000000111 !
b1010000000000111 -
1$
0&
#120000
0"
#121000
b0 ,
b0 !
b0 -
b0 #
b0 *
b1000 (
0$
b10001 )
#125000
1"
#126000
b11 ,
b1010000000000011 !
b1010000000000011 -
b1111000011110000 %
b1111000011110000 +
b11 #
b11 *
1$
1&
b10010 )
#130000
0"
#135000
b1111000011110000 !
b1111000011110000 -
1"
#136000
b0 !
b0 -
b1000000010000 %
b1000000010000 +
0&
0$
b10011 )
#140000
0"
#145000
1"
#146000
b1111000011110000 !
b1111000011110000 -
1$
#150000
0"
#151000
b0 !
b0 -
0$
b10100 )
