Practical-4_Joab/src/Parameter.v
// =========================================================================
// Practical 4: StarCore-1 — Single-Cycle Processor in Verilog
// =========================================================================
//
// GROUP NUMBER:7
//
// MEMBERS:
//   - Member 1 Joab Gray Kloppers, KLPJOA002
//   - Member 2 Name, Student Number

// File        : Parameter.v
// Description : Shared compile-time parameters used across all modules.
//               Include this file at the top of every .v file:
//                   `include "../src/Parameter.v"
// =============================================================================

`ifndef PARAMETER_H_
`define PARAMETER_H_

// ---------------------------------------------------------------------------
// Memory dimensions
// ---------------------------------------------------------------------------
`define COL     16          // Data/instruction word width (bits)
`define ROW_I   16          // Instruction memory depth (words, 16 x 16-bit)
`define ROW_D    8          // Data memory depth (words,  8 x 16-bit)

// ---------------------------------------------------------------------------
// Simulation control
// Increase SIM_TIME if your test program needs more clock cycles to complete.
// At 10 ns per clock (100 MHz) each #10 is one half-period; 320 ns = 16 cycles.
// ---------------------------------------------------------------------------
`define SIM_TIME  #640      // Total simulation time for integration testbench

// ---------------------------------------------------------------------------
// Output file for data-memory dump (used in DataMemory.v $fmonitor)
// ---------------------------------------------------------------------------
`define DMEM_LOG  "./waves/dmem_log.txt"

`endif  // PARAMETER_H_

Practical-4_Joab/src/InstructionMemory.v
// =========================================================================
// Practical 4: StarCore-1 — Single-Cycle Processor in Verilog
// =========================================================================
//
// GROUP NUMBER: 7
//
// MEMBERS:
//   - Member 1 Joab Gray Kloppers, KLPJOA002
//   - Member 2 Name, Student Number

// File        : InstructionMemory.v
// Description : Instruction Memory (ROM).
//               16 words × 16 bits. Contents loaded at simulation start from
//               the binary file ./test/test.prog using $readmemb.
//               This is a purely combinational module — the instruction output
//               updates immediately when the PC changes. No clock input.
//
// Task 3 — Student Implementation Required
// =============================================================================

`timescale 1ns / 1ps
`include "../src/Parameter.v"

module InstructionMemory (
    input  [15:0] pc,           // Program Counter (byte address)
    output [15:0] instruction   // Fetched 16-bit instruction word
);

    // -------------------------------------------------------------------------
    // TODO: Declare the instruction memory array.
    //       It should hold `ROW_I entries, each `COL bits wide.
    //
    //       reg [`COL-1:0] memory [`ROW_I-1:0];
    // -------------------------------------------------------------------------
    reg [`COL-1:0] memory [`ROW_I-1:0];


    // -------------------------------------------------------------------------
    // TODO: Derive the word address from the byte-addressed PC.
    //
    //       Because each instruction is 16 bits (2 bytes) wide, and the PC
    //       increments by 2 each cycle, the word index into the ROM is:
    //
    //           wire [3:0] rom_addr = pc[4:1];
    //
    //       This discards the byte-select bit (pc[0], always 0 for aligned
    //       accesses) and maps the byte address to a word index:
    //           PC=0x0000 -> rom_addr=0
    //           PC=0x0002 -> rom_addr=1
    //           PC=0x0004 -> rom_addr=2   ... and so on.
    // -------------------------------------------------------------------------
    wire [3:0] rom_addr = pc[4:1];




    // -------------------------------------------------------------------------
    // TODO: Load the instruction memory contents from file at simulation start.
    //       The file ./test/test.prog must contain one 16-bit binary value
    //       per line (e.g. 0010000001010000).
    //
    //       initial begin
    //           $readmemb("./test/test.prog", memory, 0, 14);
    //       end
    //
    //       Note: the third and fourth arguments (0, 14) specify the start and
    //       end indices in the array to fill. Adjust if your program is longer.
    // -------------------------------------------------------------------------

    initial begin
        $readmemb("test.prog",memory,0,14);
    end

    // -------------------------------------------------------------------------
    // TODO: Drive the instruction output with a continuous assignment.
    //       The output must update combinationally whenever rom_addr changes.
    //
    //       assign instruction = memory[rom_addr];
    // -------------------------------------------------------------------------
    assign instruction = memory[rom_addr];


endmodule

Practical-4_Joab/tb/InstructionMemory_tb.v
// =============================================================================
// EEE4120F Practical 4 — StarCore-1 Processor
// File        : InstructionMemory_tb.v
// Description : Testbench for the Instruction Memory module (Task 3).
//               Walks the PC through all valid addresses and verifies the
//               correct instruction word is output combinationally.
//
// Run:
//   iverilog -Wall -I ../src -o ../build/im_sim ../src/InstructionMemory.v InstructionMemory_tb.v
//   cd ../test && ../build/im_sim
//   gtkwave ../waves/im_tb.vcd &
// =============================================================================

`timescale 1ns / 1ps
`include "../src/Parameter.v"

module InstructionMemory_tb;

    reg  [15:0] pc;
    wire [15:0] instruction;

    InstructionMemory uut (.pc(pc), .instruction(instruction));

    initial begin
        $dumpfile("../waves/im_tb.vcd");
        $dumpvars(0, InstructionMemory_tb);
    end

    integer fail_count;
    integer test_id;
    integer i;
    // Expected instruction words — these must match the contents of test.prog.
    // Update these values after you finalise your test.prog file.
    reg [15:0] expected [0:14];

    initial begin
        fail_count = 0;
        test_id    = 1;

        $display("=== InstructionMemory Testbench ===");

        // TODO: Load the expected values to match your test.prog file.
        //       For example, if your first instruction is ADD R2,R0,R1 (0010000001010000):
        //           expected[0]  = 16'b0010000001010000;
        //       Fill in all 15 entries to match your test.prog exactly.
        //
        //       expected[0]  = 16'bXXXXXXXXXXXXXXXX;
        //       expected[1]  = 16'bXXXXXXXXXXXXXXXX;
        //       ... (fill all 15)

        expected[0] = 16'b0000010000000000;
        expected[1] = 16'b0000010001000001;
        expected[2] = 16'b0010000001010000;
        expected[3] = 16'b0001001010000000;
        expected[4] = 16'b0011000001010000;
        expected[5] = 16'b0111000001010000;
        expected[6] = 16'b1000000001010000;
        expected[7] = 16'b1001000001010000;
        expected[8] = 16'b0010000000000000;
        expected[9] = 16'b1011000001000001;
        expected[10] = 16'b1100000001000000;
        expected[11] = 16'b1101000000000000;
        expected[12] = 16'b0000000000000000;
        expected[13] = 16'b0000000000000000;
        expected[14] = 16'b0000000000000000;


        // TODO: Walk PC through addresses 0, 2, 4, ... 28 (14 instructions).
        //       At each address, verify instruction == expected[rom_index].
        //       Verify also that the output is combinational (no clock needed).
        //
        //       For each address:
        //           pc = 16'd0; #5;  // set PC, wait for combinational output
        //           if (instruction !== expected[0])
        //               $display("FAIL [T%0d]: PC=0 got %b exp %b",
        //                        test_id, instruction, expected[0]);
        //           else
        //               $display("PASS [T%0d]: PC=0 instr=%b", test_id, instruction);
        //           test_id = test_id + 1;
        //
        //           pc = 16'd2; #5;
        //           ... and so on.

        
        for (i=0 ; i <= 14; i = i+1) begin
            pc = i*2; #5;

            if (instruction !== expected[i])
                $display("FAIL [T%0d]: PC=%0d got %b exp %b",
                        test_id,pc, instruction, expected[i]);
            else
                $display("PASS [T%0d]: PC=%0d instr=%b", test_id,pc, instruction);
            test_id = test_id + 1;
        end

        $display("");
        if (fail_count == 0)
            $display("=== ALL %0d TESTS PASSED ===", test_id - 1);
        else
            $display("=== %0d / %0d TESTS FAILED ===", fail_count, test_id - 1);
        $finish;
    end

endmodule

Practical-4_Joab/waves/im_tb.vcd
$date
	Mon Apr 20 15:26:54 2026
$end
$version
	Icarus Verilog
$end
$timescale
	1ps
$end
$scope module InstructionMemory_tb $end
$var wire 16 ! instruction [15:0] $end
$var reg 16 " pc [15:0] $end
$var integer 32 # fail_count [31:0] $end
$var integer 32 $ i [31:0] $end
$var integer 32 % test_id [31:0] $end
$scope module uut $end
$var wire 16 & instruction [15:0] $end
$var wire 16 ' pc [15:0] $end
$var wire 4 ( rom_addr [3:0] $end
$upscope $end
$upscope $end
$enddefinitions $end
$comment Show the parameter values. $end
$dumpall
$end
#0
$dumpvars
b0 (
b0 '
b10000000000 &
b1 %
b0 $
b0 #
b0 "
b10000000000 !
$end
#5000
b10001000001 !
b10001000001 &
b1 (
b10 "
b10 '
b1 $
b10 %
#10000
b10000001010000 !
b10000001010000 &
b10 (
b100 "
b100 '
b10 $
b11 %
#15000
b1001010000000 !
b1001010000000 &
b11 (
b110 "
b110 '
b11 $
b100 %
#20000
b11000001010000 !
b11000001010000 &
b100 (
b1000 "
b1000 '
b100 $
b101 %
#25000
b111000001010000 !
b111000001010000 &
b101 (
b1010 "
b1010 '
b101 $
b110 %
#30000
b1000000001010000 !
b1000000001010000 &
b110 (
b1100 "
b1100 '
b110 $
b111 %
#35000
b1001000001010000 !
b1001000001010000 &
b111 (
b1110 "
b1110 '
b111 $
b1000 %
#40000
b10000000000000 !
b10000000000000 &
b1000 (
b10000 "
b10000 '
b1000 $
b1001 %
#45000
b1011000001000001 !
b1011000001000001 &
b1001 (
b10010 "
b10010 '
b1001 $
b1010 %
#50000
b1100000001000000 !
b1100000001000000 &
b1010 (
b10100 "
b10100 '
b1010 $
b1011 %
#55000
b1101000000000000 !
b1101000000000000 &
b1011 (
b10110 "
b10110 '
b1011 $
b1100 %
#60000
b0 !
b0 &
b1100 (
b11000 "
b11000 '
b1100 $
b1101 %
#65000
b1101 (
b11010 "
b11010 '
b1101 $
b1110 %
#70000
b1110 (
b11100 "
b11100 '
b1110 $
b1111 %
#75000
b1111 $
b10000 %
